easyborg/__main__.py
easyborg/borg.py
easyborg/cli.py
easyborg/config.py
easyborg/context.py
easyborg/cron.py
easyborg/fzf.py
easyborg/interaction.py
easyborg/log_utils.py
easyborg/model.py
easyborg/process.py
easyborg/progress_parser.py
easyborg/theme.py
easyborg/ui.py
easyborg/util.py
easyborg/command/__init__.py
easyborg/command/archive.py
easyborg/command/backup.py
easyborg/command/delete.py
easyborg/command/doctor.py
easyborg/command/extract.py
easyborg/command/open.py
easyborg/command/replace.py
easyborg/command/restore.py
easyborg/resources/template-easyborg.toml
easyborg-1.0.1.dist-info/licenses/LICENSE
easyborg-1.0.1.dist-info/METADATA
easyborg-1.0.1.dist-info/WHEEL
easyborg-1.0.1.dist-info/entry_points.txt
easyborg-1.0.1.dist-info/top_level.txt
easyborg-1.0.1.dist-info/RECORD
