Metadata-Version: 2.4
Name: easyborg
Version: 1.0.1
Summary: Borg for Dummies
Author-email: Sebastian Haberey <sebastian@haberey.com>
License-Expression: MIT
Project-URL: Homepage, https://github.com/sebastianhaberey/easyborg
Project-URL: Repository, https://github.com/sebastianhaberey/easyborg
Project-URL: Bug Tracker, https://github.com/sebastianhaberey/easyborg/issues
Project-URL: Changelog, https://github.com/sebastianhaberey/easyborg/blob/main/CHANGELOG.md
Classifier: Programming Language :: Python :: 3
Classifier: Programming Language :: Python :: 3 :: Only
Classifier: Programming Language :: Python :: 3.10
Classifier: Programming Language :: Python :: 3.11
Classifier: Programming Language :: Python :: 3.12
Classifier: Programming Language :: Python :: 3.13
Classifier: Programming Language :: Python :: 3.14
Classifier: Operating System :: MacOS :: MacOS X
Classifier: Operating System :: POSIX :: Linux
Classifier: Environment :: Console
Classifier: Topic :: System :: Archiving :: Backup
Classifier: Topic :: Utilities
Requires-Python: >=3.10
License-File: LICENSE
Requires-Dist: click>=8.3.1
Requires-Dist: cloup>=3.0.8
Requires-Dist: rich>=14.2.0
Requires-Dist: platformdirs>=4.5.1
Provides-Extra: dev
Requires-Dist: pytest>=9.0.1; extra == "dev"
Requires-Dist: ruff>=0.14.5; extra == "dev"
Dynamic: license-file
